mfinancials/__init__.py
mfinancials/_tickers.py
mfinancials/base.py
mfinancials/params.py
mfinancials/ticker.py
mfinancials/utils.py
mfinancials-0.0.2.dist-info/LICENSE
mfinancials-0.0.2.dist-info/METADATA
mfinancials-0.0.2.dist-info/WHEEL
mfinancials-0.0.2.dist-info/top_level.txt
mfinancials-0.0.2.dist-info/RECORD
