Metadata-Version: 2.1
Name: mfinancials
Version: 0.0.2
Summary: Simple module for downloading financial statements and estimates from financials.morningstar.com
Home-page: https://github.com/tobigs/mfinancials
Author: Tobias Seidel
Author-email: tobiasseidel@mail.de
License: UNKNOWN
Project-URL: Bug Tracker, https://github.com/tobigs/mfinancials/issues
Keywords: pandas,morningstar financials
Platform: UNKNOWN
Classifier: Programming Language :: Python :: 3
Classifier: License :: OSI Approved :: MIT License
Classifier: Development Status :: 3 - Alpha
Classifier: Operating System :: OS Independent
Classifier: Intended Audience :: Developers
Classifier: Topic :: Office/Business :: Financial
Classifier: Topic :: Office/Business :: Financial :: Investment
Classifier: Topic :: Scientific/Engineering :: Interface Engine/Protocol Translator
Classifier: Topic :: Software Development :: Libraries
Classifier: Topic :: Software Development :: Libraries :: Python Modules
Requires-Python: >=3.6
License-File: LICENSE
Requires-Dist: beautifulsoup4 (>=4.9.1)
Requires-Dist: numpy (>=1.18.5)
Requires-Dist: requests (>=2.24.0)
Requires-Dist: yfinance (>=0.1.54)
Requires-Dist: pandas (>=1.1.2)
Requires-Dist: lxml (>=4.5.2)
